{
  "project_info": {
    "project_number": "329708522429",
    "project_id": "ielts-hunter-6db1e",
    "storage_bucket": "ielts-hunter-6db1e.appspot.com"
  },
  "client": [
    {
      "client_info": {
        "mobilesdk_app_id": "1:329708522429:android:794ddc4e1762d973c520d4",
        "android_client_info": {
          "package_name": "com.ikigroup.ieltshunter"
        }
      },
      "oauth_client": [
        {
          "client_id": "329708522429-0bh4qgukdsuampv1j93jhg2p229opael.apps.googleusercontent.com",
          "client_type": 1,
          "android_info": {
            "package_name": "com.ikigroup.ieltshunter",
            "certificate_hash": "cba9a039c8505fd67e968a6d76471d2594e3b0ba"
          }
        },
        {
          "client_id": "329708522429-70tqrqnq4gd4obv406svc87ck784t4vv.apps.googleusercontent.com",
          "client_type": 1,
          "android_info": {
            "package_name": "com.ikigroup.ieltshunter",
            "certificate_hash": "7b1c4a1ec86fc4102165038b5c4aef661be5502c"
          }
        },
        {
          "client_id": "329708522429-ee5ng34sgu7gtqc23ff3dospevslcjuq.apps.googleusercontent.com",
          "client_type": 1,
          "android_info": {
            "package_name": "com.ikigroup.ieltshunter",
            "certificate_hash": "2b1f34c90ad7897a635ed3b62ce9a24e5c9739ce"
          }
        },
        {
          "client_id": "329708522429-pnnnpnnren9h43qspvuito9p2hpq7j8o.apps.googleusercontent.com",
          "client_type": 1,
          "android_info": {
            "package_name": "com.ikigroup.ieltshunter",
            "certificate_hash": "9337d4bd4a04789ec038086b9a3b339008cda81f"
          }
        },
        {
          "client_id": "329708522429-t56qqqgo9kasu9rqtomf1aj8al55obbo.apps.googleusercontent.com",
          "client_type": 3
        }
      ],
      "api_key": [
        {
          "current_key": "AIzaSyB0PNST3hmbS9TchbkgYwgVA0zOMNmMZWo"
        }
      ],
      "services": {
        "appinvite_service": {
          "other_platform_oauth_client": [
            {
              "client_id": "329708522429-t56qqqgo9kasu9rqtomf1aj8al55obbo.apps.googleusercontent.com",
              "client_type": 3
            },
            {
              "client_id": "329708522429-tb80b2s4u8k8r3p2ocn5rfa5ofr78kbl.apps.googleusercontent.com",
              "client_type": 2,
              "ios_info": {
                "bundle_id": "com.ikigroup.ieltshunter",
                "app_store_id": "6478486893"
              }
            }
          ]
        }
      }
    },
    {
      "client_info": {
        "mobilesdk_app_id": "1:329708522429:android:f76f0b92dd86aacec520d4",
        "android_client_info": {
          "package_name": "com.ikigroup.ieltshunterpro"
        }
      },
      "oauth_client": [
        {
          "client_id": "329708522429-8dfvga2ak4e5hi6e9b1otjhd0l4vghvg.apps.googleusercontent.com",
          "client_type": 1,
          "android_info": {
            "package_name": "com.ikigroup.ieltshunterpro",
            "certificate_hash": "27d4fb19ca06b965e315a55acd79c46ce792a2a4"
          }
        },
        {
          "client_id": "329708522429-a5bajo6dfl0jimemlaj505j506o0kdqp.apps.googleusercontent.com",
          "client_type": 1,
          "android_info": {
            "package_name": "com.ikigroup.ieltshunterpro",
            "certificate_hash": "bf726b653a1dc4053f77f04d93a38e332400b324"
          }
        },
        {
          "client_id": "329708522429-rh2oc0uqcqhss697l66phbpoc1s2mfs9.apps.googleusercontent.com",
          "client_type": 1,
          "android_info": {
            "package_name": "com.ikigroup.ieltshunterpro",
            "certificate_hash": "b6f642694ad088f23339676a962c1206f6e36dd3"
          }
        },
        {
          "client_id": "329708522429-t56qqqgo9kasu9rqtomf1aj8al55obbo.apps.googleusercontent.com",
          "client_type": 3
        }
      ],
      "api_key": [
        {
          "current_key": "AIzaSyB0PNST3hmbS9TchbkgYwgVA0zOMNmMZWo"
        }
      ],
      "services": {
        "appinvite_service": {
          "other_platform_oauth_client": [
            {
              "client_id": "329708522429-t56qqqgo9kasu9rqtomf1aj8al55obbo.apps.googleusercontent.com",
              "client_type": 3
            },
            {
              "client_id": "329708522429-tb80b2s4u8k8r3p2ocn5rfa5ofr78kbl.apps.googleusercontent.com",
              "client_type": 2,
              "ios_info": {
                "bundle_id": "com.ikigroup.ieltshunter",
                "app_store_id": "6478486893"
              }
            }
          ]
        }
      }
    }
  ],
  "configuration_version": "1"
}